{"v":"5.5.9","fr":60,"ip":0,"op":16,"w":30,"h":30,"nm":"iconFavoriteLight","ddd":0,"assets":[],"layers":[{"ddd":0,"ind":1,"ty":4,"nm":"icon_Favorites Outlines 2","sr":0.75,"ks":{"o":{"a":0,"k":100,"ix":11},"r":{"a":0,"k":0,"ix":10},"p":{"a":0,"k":[15,15,0],"ix":2},"a":{"a":0,"k":[15,15,0],"ix":1},"s":{"a":1,"k":[{"i":{"x":[0.667,0.667,0.667],"y":[1,1,1]},"o":{"x":[0.167,0.167,0.167],"y":[0,0,0]},"t":0,"s":[100,100,100]},{"i":{"x":[0.667,0.667,0.667],"y":[1,1,1]},"o":{"x":[0.333,0.333,0.333],"y":[0,0,0]},"t":1,"s":[100,100,100]},{"i":{"x":[0.667,0.667,0.667],"y":[1,1,1]},"o":{"x":[0.333,0.333,0.333],"y":[0,0,0]},"t":8,"s":[110,131,100]},{"t":15,"s":[100,100,100]}],"ix":6}},"ao":0,"shapes":[{"ty":"gr","it":[{"ind":0,"ty":"sh","ix":1,"ks":{"a":0,"k":{"i":[[2.322,0],[0,-2.626],[-5.173,-3.356],[0,5.68],[4.157,0],[1.487,-1.549]],"o":[[-4.155,0],[0,5.68],[5.173,-3.357],[0,-2.626],[-2.322,0],[-1.488,-1.549]],"v":[[-5.793,-10.07],[-12.5,-3.88],[0,10.07],[12.5,-3.88],[5.793,-10.07],[0,-6.889]],"c":true},"ix":2},"nm":"Path 1","mn":"ADBE Vector Shape - Group","hd":false},{"ty":"fl","c":{"a":1,"k":[{"i":{"x":[0.833],"y":[0.833]},"o":{"x":[0.167],"y":[0.167]},"t":0,"s":[0.521568655968,0.505882382393,0.600000023842,1]},{"t":0.9990234375,"s":[0.800000011921,0.058823529631,0.878431379795,1]}],"ix":4},"o":{"a":0,"k":100,"ix":5},"r":1,"bm":0,"nm":"Fill 1","mn":"ADBE Vector Graphic - Fill","hd":false},{"ty":"tr","p":{"a":0,"k":[15,15],"ix":2},"a":{"a":0,"k":[0,0],"ix":1},"s":{"a":0,"k":[100,100],"ix":3},"r":{"a":0,"k":0,"ix":6},"o":{"a":0,"k":100,"ix":7},"sk":{"a":0,"k":0,"ix":4},"sa":{"a":0,"k":0,"ix":5},"nm":"Transform"}],"nm":"Group 1","np":2,"cix":2,"bm":0,"ix":1,"mn":"ADBE Vector Group","hd":false}],"ip":0,"op":16,"st":7.5,"bm":0}],"markers":[]}