[
  {
    "annotations": {
      "__alertId__": "Y4Tx_K3nz_056_P3_prod",
      "__dashboardUid__": "Y4Tx_K3nz",
      "__panelId__": "56",
      "description": "",
      "runbook_url": "http://grafana.audius.co/d/Y4Tx_K3nz?viewPanel=56",
      "summary": ""
    },
    "condition": "B",
    "data": [
      {
        "datasourceUid": "r2_nnDL7z",
        "model": {
          "datasource": {
            "type": "prometheus",
            "uid": "r2_nnDL7z"
          },
          "expr": "(sum without (run_id,instance) (audius_nm_fully_synced_user_count{environment=~\"prod\"}) / sum without (run_id,instance) (audius_nm_user_count{environment=~\"prod\"})) * 100",
          "hide": false,
          "intervalMs": 1000,
          "maxDataPoints": 43200,
          "refId": "A"
        },
        "queryType": "",
        "refId": "A",
        "relativeTimeRange": {
          "from": 600,
          "to": 0
        }
      },
      {
        "datasourceUid": "-100",
        "model": {
          "conditions": [
            {
              "evaluator": {
                "params": [
                  80,
                  0
                ],
                "type": "lt"
              },
              "operator": {
                "type": "or"
              },
              "query": {
                "params": [
                  "A"
                ]
              },
              "reducer": {
                "params": [],
                "type": "last"
              },
              "type": "query"
            }
          ],
          "datasource": {
            "name": "Expression",
            "type": "__expr__",
            "uid": "__expr__"
          },
          "hide": false,
          "intervalMs": 1000,
          "maxDataPoints": 43200,
          "refId": "B",
          "type": "classic_conditions"
        },
        "queryType": "",
        "refId": "B",
        "relativeTimeRange": {
          "from": 0,
          "to": 0
        }
      }
    ],
    "execErrState": "Alerting",
    "folderUID": "gtl7D0W4z",
    "for": "0s",
    "id": 705631,
    "labels": {
      "alert": "p3",
      "env": "prod",
      "mentions": "@johannes",
      "team": "content"
    },
    "noDataState": "OK",
    "orgID": 1,
    "ruleGroup": "group",
    "title": "PROD P3 | User Status Percent (over time)",
    "uid": "Y4Tx_K3nz_056_P3_prod"
  }
]